[
  {
    "FIN_ACCOUNT_ID": "AHLI_CHECKING",
    "STATUS_ID": "FNACT_ACTIVE",
    "STATUS_DATE": "2009-04-01 00:00:01.000",
    "STATUS_END_DATE": null,
    "CHANGE_BY_USER_LOGIN_ID": null,
    "LAST_UPDATED_STAMP": "2022-05-27 12:24:33.037",
    "LAST_UPDATED_TX_STAMP": "2022-05-27 12:24:28.340",
    "CREATED_STAMP": "2022-05-27 12:24:33.037",
    "CREATED_TX_STAMP": "2022-05-27 12:24:28.340"
  },
  {
    "FIN_ACCOUNT_ID": "AMEX_01",
    "STATUS_ID": "FNACT_ACTIVE",
    "STATUS_DATE": "2009-04-01 00:00:01.000",
    "STATUS_END_DATE": null,
    "CHANGE_BY_USER_LOGIN_ID": null,
    "LAST_UPDATED_STAMP": "2022-05-27 12:24:33.057",
    "LAST_UPDATED_TX_STAMP": "2022-05-27 12:24:28.340",
    "CREATED_STAMP": "2022-05-27 12:24:33.057",
    "CREATED_TX_STAMP": "2022-05-27 12:24:28.340"
  },
  {
    "FIN_ACCOUNT_ID": "SC_CHECKING",
    "STATUS_ID": "FNACT_ACTIVE",
    "STATUS_DATE": "2009-04-01 00:00:01.000",
    "STATUS_END_DATE": null,
    "CHANGE_BY_USER_LOGIN_ID": null,
    "LAST_UPDATED_STAMP": "2022-05-27 12:24:32.997",
    "LAST_UPDATED_TX_STAMP": "2022-05-27 12:24:28.340",
    "CREATED_STAMP": "2022-05-27 12:24:32.997",
    "CREATED_TX_STAMP": "2022-05-27 12:24:28.340"
  }
]